crownstone_sdk-1.0.0.data/scripts/cs_dfu_write_application
crownstone_sdk-1.0.0.data/scripts/cs_factory_reset_crownstone
crownstone_sdk-1.0.0.data/scripts/cs_microapp_enable
crownstone_sdk-1.0.0.data/scripts/cs_microapp_message
crownstone_sdk-1.0.0.data/scripts/cs_microapp_upload
crownstone_sdk-1.0.0.data/scripts/cs_scan_any_crownstone
crownstone_sdk-1.0.0.data/scripts/cs_scan_for_alternative_state
crownstone_sdk-1.0.0.data/scripts/cs_scan_known_crownstones
crownstone_sdk-1.0.0.data/scripts/cs_setup_crownstone
crownstone_sdk-1.0.0.data/scripts/cs_switch_crownstone
tools/__init__.py
tools/config/__init__.py
tools/dfu/__init__.py
tools/dfu/ble_uuid.py
tools/dfu/dfu_constants.py
tools/dfu/dfu_exceptions.py
tools/dfu/dfu_transport_ble.py
tools/util/__init__.py
tools/util/config.py
crownstone_sdk-1.0.0.dist-info/LICENSE-APACHE
crownstone_sdk-1.0.0.dist-info/LICENSE-LGPL
crownstone_sdk-1.0.0.dist-info/LICENSE-MIT
crownstone_sdk-1.0.0.dist-info/METADATA
crownstone_sdk-1.0.0.dist-info/WHEEL
crownstone_sdk-1.0.0.dist-info/top_level.txt
crownstone_sdk-1.0.0.dist-info/RECORD
