Metadata-Version: 2.1
Name: crownstone-sdk
Version: 1.0.0
Summary: UNKNOWN
Home-page: https://github.com/crownstone/crownstone-python-sdk
Author: Crownstone B.V.
License: UNKNOWN
Platform: UNKNOWN
Classifier: Programming Language :: Python :: 3.7
Requires-Python: >=3.7
Requires-Dist: crownstone-ble (~=2.6)
Requires-Dist: crownstone-uart (~=2.7)
Requires-Dist: bluenet-logs (~=1.2)
Requires-Dist: bleak (==0.10)
